pytest_contexts.py
pytest_contexts-0.1.2.dist-info/METADATA
pytest_contexts-0.1.2.dist-info/RECORD
pytest_contexts-0.1.2.dist-info/WHEEL
pytest_contexts-0.1.2.dist-info/entry_points.txt
pytest_contexts-0.1.2.dist-info/top_level.txt
