Metadata-Version: 2.1
Name: pytest-contexts
Version: 0.1.2
Summary: A plugin to run tests written with the Contexts framework using pytest
Home-page: https://github.com/madedotcom/pytest-contexts
Author: Harry Percival
Author-email: obeythetestinggoat@gmail.com
Maintainer: Harry Percival
Maintainer-email: obeythetestinggoat@gmail.com
License: GNU GPL v3.0
Platform: UNKNOWN
Classifier: Development Status :: 4 - Beta
Classifier: Framework :: Pytest
Classifier: Intended Audience :: Developers
Classifier: Topic :: Software Development :: Testing
Classifier: Programming Language :: Python
Classifier: Programming Language :: Python :: 3.6
Classifier: Programming Language :: Python :: 3.7
Classifier: Operating System :: OS Independent
Classifier: License :: OSI Approved :: GNU General Public License v3 (GPLv3)
Requires-Python: >=3.6
Requires-Dist: pytest
Requires-Dist: contexts
